ircstates/__init__.py
ircstates/casemap.py
ircstates/channel.py
ircstates/channel_user.py
ircstates/decorators.py
ircstates/emit.py
ircstates/names.py
ircstates/numerics.py
ircstates/py.typed
ircstates/server.py
ircstates/user.py
ircstates/isupport/__init__.py
ircstates/isupport/tokens.py
test/__init__.py
test/cap.py
test/casemap.py
test/channel.py
test/emit.py
test/isupport.py
test/mode.py
test/motd.py
test/sasl.py
test/user.py
test/who.py
ircstates-0.13.0.dist-info/LICENSE
ircstates-0.13.0.dist-info/METADATA
ircstates-0.13.0.dist-info/WHEEL
ircstates-0.13.0.dist-info/top_level.txt
ircstates-0.13.0.dist-info/RECORD
