Metadata-Version: 2.1
Name: ircstates
Version: 0.13.0
Summary: IRC client session state parsing library
Home-page: https://github.com/jesopo/ircstates
Author: jesopo
Author-email: pip@jesopo.uk
Classifier: Programming Language :: Python :: 3
Classifier: License :: OSI Approved :: MIT License
Classifier: Operating System :: OS Independent
Classifier: Operating System :: POSIX
Classifier: Operating System :: Microsoft :: Windows
Classifier: Topic :: Communications :: Chat :: Internet Relay Chat
Requires-Python: >=3.8
License-File: LICENSE
Requires-Dist: irctokens (~=2.0.2)
Requires-Dist: pendulum (~=3.0.0)
